congler/__init__.py
congler-0.5.0.dist-info/DESCRIPTION.rst
congler-0.5.0.dist-info/METADATA
congler-0.5.0.dist-info/RECORD
congler-0.5.0.dist-info/WHEEL
congler-0.5.0.dist-info/entry_points.txt
congler-0.5.0.dist-info/metadata.json
congler-0.5.0.dist-info/top_level.txt
