Metadata-Version: 2.0
Name: congler
Version: 0.5.0
Summary: Search and delete consul services
Home-page: https://github.com/flypenguin/python-congler
Author: Axel Bock
Author-email: mr.axel.bock@gmail.com
License: UNKNOWN
Download-URL: https://github.com/flypenguin/python-congler/tarball/0.5.0
Keywords: consul,cli
Platform: UNKNOWN
Classifier: License :: OSI Approved :: MIT License
Classifier: Development Status :: 5 - Production/Stable
Classifier: Intended Audience :: Developers
Classifier: Intended Audience :: System Administrators
Classifier: Programming Language :: Python :: 3 :: Only
Classifier: Programming Language :: Python :: 3.5
Classifier: Programming Language :: Python :: 3.6
Classifier: Programming Language :: Python :: Implementation :: CPython
Classifier: Operating System :: POSIX
Classifier: Operating System :: MacOS
Classifier: Topic :: System :: Systems Administration
Requires-Dist: python-consul (==0.7.0)
